simplelogin/__init__.py
simplelogin/client.py
simplelogin/exceptions.py
simplelogin/definitions/__init__.py
simplelogin/definitions/data/__init__.py
simplelogin/definitions/data/account.py
simplelogin/definitions/data/alias.py
simplelogin/definitions/data/mailbox.py
simplelogin/definitions/endpoints/__init__.py
simplelogin/definitions/endpoints/account.py
simplelogin/definitions/endpoints/alias.py
simplelogin/definitions/endpoints/mailbox.py
tests/__init__.py
tests/main.py
tests/test_alias_api.py
tests/test_user_api.py
simplelogin_api-0.1.1.dist-info/LICENSE
simplelogin_api-0.1.1.dist-info/METADATA
simplelogin_api-0.1.1.dist-info/WHEEL
simplelogin_api-0.1.1.dist-info/top_level.txt
simplelogin_api-0.1.1.dist-info/RECORD
