Metadata-Version: 2.1
Name: simplelogin-api
Version: 0.1.1
Summary: SimpleLogin API wrapper
Home-page: https://github.com/vixfwis/simplelogin-api
Author: vixfwis
License: UNKNOWN
Platform: UNKNOWN
License-File: LICENSE
Requires-Dist: attrs (==21.4.0)
Requires-Dist: certifi (==2021.10.8)
Requires-Dist: charset-normalizer (==2.0.12)
Requires-Dist: idna (==3.3)
Requires-Dist: iniconfig (==1.1.1)
Requires-Dist: packaging (==21.3)
Requires-Dist: pluggy (==1.0.0)
Requires-Dist: py (==1.11.0)
Requires-Dist: pyparsing (==3.0.8)
Requires-Dist: pytest (==7.1.1)
Requires-Dist: requests (==2.27.1)
Requires-Dist: schematics (==2.1.1)
Requires-Dist: tomli (==2.0.1)
Requires-Dist: urllib3 (==1.26.9)
